ciri_db_tools.py
ciri_db_tools-1.1.1.dist-info/METADATA
ciri_db_tools-1.1.1.dist-info/WHEEL
ciri_db_tools-1.1.1.dist-info/licenses/LICENSE
ciri_db_tools-1.1.1.dist-info/RECORD
