Metadata-Version: 2.1
Name: ciri_db_tools
Version: 1.1.1
Summary: Some database manipulation tools
Project-URL: Homepage, https://github.com/cat-cfs/ciri_results_db
Author-email: Sasha Vujisic <sva39@sfu.ca>
License-File: LICENSE
Classifier: License :: OSI Approved :: MIT License
Classifier: Operating System :: OS Independent
Classifier: Programming Language :: Python :: 3
Requires-Python: >=3.7
